[
    {
        "nombre": "Archivos",
        "elementosUnicos": false,
        "valoresGuardar": [
            { 
                "clave": "path", "tipo": "string", "largo": 400,
                "representativo": true, "necesario": true
            }
        ]
    },
    {
        "nombre": "Tags",
        "elementosUnicos": true,
        "valoresGuardar": [
            { 
                "clave": "tag", "tipo": "string", "largo": 255,
                "representativo": true, "necesario": true
            }
        ],
        "referenciasTabla": [
            { "tabla": "Archivos", "clave": "refArchivo" }
        ]
    },
    {
        "nombre": "Personas",
        "elementosUnicos": true,
        "valoresGuardar": [
            { 
                "clave": "nombre", "tipo": "string", "largo": 255,
                "representativo": true, "necesario": true
            },
            { 
                "clave": "apellido", "tipo": "string", "largo": 255,
                "representativo": true, "necesario": true
            }
        ]
    },
    {
        "nombre": "Editoriales",
        "elementosUnicos": true,
        "valoresGuardar": [
            { 
                "clave": "editorial", "tipo": "string", "largo": 255,
                "representativo": true, "necesario": true
            }
        ]
    }, 
    {
        "nombre": "Libros",
        "elementosUnicos": false,
        "valoresGuardar": [
            { 
                "clave": "titulo", "tipo": "string", "largo": 255,
                "representativo": true, "necesario": true
            },
            { 
                "clave": "subtitulo", "tipo": "string", "largo": 255,
                "necesario": false
            },
            { 
                "clave": "anio", "tipo": "int", 
                "representativo": true, "necesario": true
            },
            { 
                "clave": "edicion", "tipo": "int", 
                "representativo": true, "necesario": true
            },
            { 
                "clave": "volumen", "tipo": "int", 
                "representativo": true, "necesario": true
            },
            { 
                "clave": "url", "tipo": "string", "largo": 255,
                "necesario": false
            }
        ],
        "referenciasTabla": [
            { "tabla": "Archivos", "clave": "refArchivo" },
            { "tabla": "Editoriales", "clave": "refEditorial" }
        ]
    },
    {
        "nombre": "AutoresLibro",
        "elementosUnicos": false,
        "referenciasTabla": [
            { "tabla": "Libros", "clave": "refLibro" },
            { "tabla": "Personas", "clave": "refPersona" }
        ]
    },
    {
        "nombre": "Capitulos",
        "elementosUnicos": false,
        "valoresGuardar": [
            { 
                "clave": "numero", "tipo": "int", 
                "representativo": true, "necesario": true
            },
            { 
                "clave": "nombre", "tipo": "string", "largo": 255,
                "representativo": true, "necesario": true
            },
            { 
                "clave": "paginaInicio", "tipo": "int", 
                "representativo": true, "necesario": true
            },
            { 
                "clave": "paginaFinal", "tipo": "int", 
                "representativo": true, "necesario": true
            }
        ],
        "referenciasTabla": [
            { "tabla": "Archivos", "clave": "refArchivo" },
            { "tabla": "Libros", "clave": "refLibro" }
        ]
    },
    {
        "nombre": "EditoresCapitulo",
        "elementosUnicos": false,
        "referenciasTabla": [
            { "tabla": "Capitulos", "clave": "refCapitulo" },
            { "tabla": "Personas", "clave": "refPersona" }
        ]
    },
    {
        "nombre": "Carreras",
        "elementosUnicos": false,
        "valoresGuardar": [
            { 
                "clave": "nombre", "tipo": "string", "largo": 255,
                "representativo": true, "necesario": true
            },
            { 
                "clave": "etapa", "tipo": "enum", "valores": ["SinEmpezar", "Empezado", "Ampliar", "Terminado"], 
                "representativo": false, "necesario": true
            },
            { 
                "clave": "tieneCodigoMateria", "tipo": "bool", 
                "representativo": false, "necesario": true
            }
        ],
        "referenciasTabla": [
            { "tabla": "Archivos", "clave": "refArchivo" }
        ]
    },
    {
        "nombre": "Distribuciones",
        "elementosUnicos": false,
        "valoresGuardar": [
            {
                "clave": "nombre", "tipo": "string", "largo": 255,
                "representativo": true, "necesario": true
            },
            {
                "clave": "tipo", "tipo": "enum", "valores": ["Discreta", "Continua", "Multivariada"],
                "representativo": false, "necesario": true
            }
        ],
        "referenciasTabla": [
            { "tabla": "Archivos", "clave": "refArchivo" }
        ]
    },
    {
        "nombre": "RelacionesDistribuciones",
        "elementosUnicos": false,
        "referenciasTabla": [
            { "tabla": "Archivos", "clave": "refArchivo" },
            { "tabla": "Distribuciones", "clave": "refDistribucionA" },
            { "tabla": "Distribuciones", "clave": "refDistribucionB" }
        ]
    }
]